pw_stats/__init__.py
pw_stats/py.typed
pw_stats/stats.py
pw_stats-2.0.1.dist-info/LICENSE
pw_stats-2.0.1.dist-info/METADATA
pw_stats-2.0.1.dist-info/WHEEL
pw_stats-2.0.1.dist-info/top_level.txt
pw_stats-2.0.1.dist-info/zip-safe
pw_stats-2.0.1.dist-info/RECORD
