Metadata-Version: 2.1
Name: pw-stats
Version: 2.0.1
Summary: validation of passwords and their statistics in python, modern, async and cached rewrite of https://pypi.org/project/password-strength/
Home-page: https://ari-web.xyz/gh/pw_stats
Author: Ari Archer
Author-email: ari.web.xyz@gmail.com
License: GPLv3+
Keywords: password,strength,statistics,passwords,security,validation,async,modern,stats,entropy,caching
Classifier: Development Status :: 5 - Production/Stable
Classifier: Intended Audience :: Developers
Classifier: License :: OSI Approved :: GNU General Public License v3 or later (GPLv3+)
Classifier: Operating System :: OS Independent
Classifier: Programming Language :: Python :: 3
Classifier: Programming Language :: Python :: 3.9
Classifier: Programming Language :: Python :: 3.10
Classifier: Programming Language :: Python :: 3.11
Classifier: Programming Language :: Python :: 3.12
Classifier: Topic :: Internet :: WWW/HTTP
Classifier: Topic :: Software Development :: Libraries :: Python Modules
Classifier: Typing :: Typed
License-File: LICENSE
Requires-Dist: async-lru
